setup.py
pkcs7/__init__.py
pkcs7.egg-info/PKG-INFO
pkcs7.egg-info/SOURCES.txt
pkcs7.egg-info/dependency_links.txt
pkcs7.egg-info/not-zip-safe
pkcs7.egg-info/top_level.txt