Metadata-Version: 1.0
Name: pkcs7
Version: 0.1.0
Summary: extension class for argparse with json configuration
Home-page: http://github.com/jeppeter/pypkcs7
Author: jeppeter Wang
Author-email: jeppeter@gmail.com
License: MIT
Platform: UNKNOWN
